ftptomongo.py
ftptomongo-0.1.0.dist-info/LICENSE
ftptomongo-0.1.0.dist-info/METADATA
ftptomongo-0.1.0.dist-info/WHEEL
ftptomongo-0.1.0.dist-info/RECORD
