Metadata-Version: 2.1
Name: ftptomongo
Version: 0.1.0
Summary: 
License: MIT
Author: Danil Kabanov
Author-email: nill2@yandex.ru
Requires-Python: >=3.11,<4.0
Classifier: License :: OSI Approved :: MIT License
Classifier: Programming Language :: Python :: 3
Classifier: Programming Language :: Python :: 3.11
